<?xml version="1.0" encoding="utf-8" ?>
<dwsync>
<file name="bootstrap_red_v2.jpg" server="18.130.132.39//C:/inetpub/wwwroot/amz.multiplemonitors.co.uk/" local="130759984800000000" remote="130759984800000000" Dst="2" />
<file name="footer.asp" server="18.130.132.39//C:/inetpub/wwwroot/amz.multiplemonitors.co.uk/" local="130703701120000000" remote="130703701120000000" Dst="2" />
<file name="footer_facebook.asp" server="18.130.132.39//C:/inetpub/wwwroot/amz.multiplemonitors.co.uk/" local="130440310340000000" remote="130440310340000000" Dst="2" />
<file name="footer_mobile.asp" server="18.130.132.39//C:/inetpub/wwwroot/amz.multiplemonitors.co.uk/" local="130444954260000000" remote="130444954260000000" Dst="2" />
<file name="header.asp" server="18.130.132.39//C:/inetpub/wwwroot/amz.multiplemonitors.co.uk/" local="130553844320000000" remote="130553844320000000" Dst="2" />
<file name="header_facebook.asp" server="18.130.132.39//C:/inetpub/wwwroot/amz.multiplemonitors.co.uk/" local="130440310340000000" remote="130440310340000000" Dst="2" />
<file name="header_mobile.asp" server="18.130.132.39//C:/inetpub/wwwroot/amz.multiplemonitors.co.uk/" local="130492240280000000" remote="130492240280000000" Dst="2" />
<file name="theme.asp" server="18.130.132.39//C:/inetpub/wwwroot/amz.multiplemonitors.co.uk/" local="130553852520000000" remote="130553852520000000" Dst="2" />
<file name="theme_settings.asp" server="18.130.132.39//C:/inetpub/wwwroot/amz.multiplemonitors.co.uk/" local="130442332620000000" remote="130442332620000000" Dst="2" />
</dwsync>