<?xml version="1.0" encoding="utf-8" ?>
<dwsync>
<file name="hoverIntent.js" server="18.130.132.39//C:/inetpub/wwwroot/amz.multiplemonitors.co.uk/" local="131116356740000000" remote="131116356740000000" Dst="2" />
<file name="hoverIntent.min.js" server="18.130.132.39//C:/inetpub/wwwroot/amz.multiplemonitors.co.uk/" local="131124737880000000" remote="131124737880000000" Dst="2" />
<file name="jquery.meanmenu.js" server="18.130.132.39//C:/inetpub/wwwroot/amz.multiplemonitors.co.uk/" local="131116356740000000" remote="131116356740000000" Dst="2" />
<file name="jquery.meanmenu.min.js" server="18.130.132.39//C:/inetpub/wwwroot/amz.multiplemonitors.co.uk/" local="131124737880000000" remote="131124737880000000" Dst="2" />
<file name="jquery.pcmenu.js" server="18.130.132.39//C:/inetpub/wwwroot/amz.multiplemonitors.co.uk/" local="131116356760000000" remote="131116356760000000" Dst="2" />
<file name="modernizr.js" server="18.130.132.39//C:/inetpub/wwwroot/amz.multiplemonitors.co.uk/" local="131116356760000000" remote="131116356760000000" Dst="2" />
<file name="superfish.js" server="18.130.132.39//C:/inetpub/wwwroot/amz.multiplemonitors.co.uk/" local="131921489420000000" remote="131921489420000000" Dst="2" />
<file name="superfish.min.js" server="18.130.132.39//C:/inetpub/wwwroot/amz.multiplemonitors.co.uk/" local="131934527040000000" remote="131934527040000000" Dst="2" />
<file name="supersubs.js" server="18.130.132.39//C:/inetpub/wwwroot/amz.multiplemonitors.co.uk/" local="131116356780000000" remote="131116356780000000" Dst="2" />
</dwsync>